setup.py
amee_distributions/Binomialdistribution.py
amee_distributions/Gaussiandistribution.py
amee_distributions/Generaldistribution.py
amee_distributions/__init__.py
amee_distributions/test.py
amee_distributions.egg-info/PKG-INFO
amee_distributions.egg-info/SOURCES.txt
amee_distributions.egg-info/dependency_links.txt
amee_distributions.egg-info/not-zip-safe
amee_distributions.egg-info/top_level.txt