Metadata-Version: 1.0
Name: amee-distributions
Version: 0.1
Summary: Gaussian distributions
Home-page: UNKNOWN
Author: Ameeta Sharma
Author-email: amsa@westchestergov.com
License: UNKNOWN
Platform: UNKNOWN
